{"doc_id": "0bb9e7e3-c90d-4723-9440-2863f72fecb4", "url": "http://archive.org/download/bahuroopgandhitamil/BAHUROOP GANDHI - TAMIL.pdf", "source": "internetarchive", "page_no": 3, "identifier": "bahuroopgandhitamil", "pdf_name": "BAHUROOP GANDHI - TAMIL.pdf", "text": "Title : பஹுரூப் காந்தி (Bahuroop Gandhi)\na Tamil translation of Ms. Anu Bandyopadhyava's\nEnglish book 'Bahuroop Gandhi'\nTranslation by : M.R. Rajagopalan\nSecretary\nYear of Publication: 1999\nNo. of Copies : 2000\nPublished by :\nGandhigram Trust\nGandhigram, Tamil Nadu\nPrinted at\nLakshmi Seva Sangham, Gandhigram Press with the permession of the author\n-\nAnu bandyopadhyaya\nPrice : Rs.30/Lakshmi Seva Sangham. Gandhigram Press Gandhigram - 624 302, Tamil Nadu\nPhone : 0451453347\nபஹுரூப் காந்தி\nபிரதம மந்திரியின் அலுவலகம், புது டில்லி.\nமுன்னுரை\nஇப் புத்தகம் சிறுவர்களுக்காக எழுதப்பட்டது. இருப்பினும் பெரியவர்களும் இப்புத்தகத்தைப் படித்துப் பயன் பெறலாம்.\nகாந்திஜி இப்போது புகழுடம்பு எய்திவிட்டார். காந்திஜியைக் கண்ணால் பார்த்திராதவர்கள், குறிப்பாக இளைய சமுதாயத்தினர் காந்திஜியை அரும்பெரும் செயல்களைப் புரிந்த மாமனிதர் என்றே எண்ணுகின்றனர். அவருடைய வாழ்விலும் ஒரு சராசரி மனிதனின் வாழ்வில் நிகழக்கூடிய சம்பவங்கள் நிகழ்ந்தன என்பதை எல்லோரும் இப்புத்தகத்தின் வாயிலாக அறியலாம்.\n(i)\n"}