{"doc_id": "61813c50-871c-4b58-ab91-ba6401f9bc61", "url": "http://archive.org/download/in.gazette.tamilnadu.2010-05-14.Extraordinary_138_Part-IV_Section-1/Extraordinary_138_Part-IV_—Section-1.pdf", "source": "internetarchive", "page_no": 88, "identifier": "in.gazette.tamilnadu.2010-05-14.Extraordinary_138_Part-IV_Section-1", "pdf_name": "Extraordinary_138_Part-IV_—Section-1.pdf", "text": "186\nTAMIL NADU GOVERNMENT GAZETTE EXTRAORDINARY\nMEMORANDUM REGARDING DELEGATED LEGISLATION\nClauses 1(2) 4(1)(d), 19 and 22 of the Bill authorize, the Government to prescribe the manner and the method if giving effect to certain provisions of the proposed Act, when enacted and brought into operation, by issuing suitable notifications or directions as the case may be.\n2. The powers delegated are normal and not of an exceptional character.\nDR. K. PONMUDY,\nMinister for Higher Education.\nM. SELVARAJ, Secretary.\n"}