{"doc_id": "3e83f3d4-7981-4b89-becd-77861f0412ea", "url": "http://archive.org/download/AMAZINGACTIVITIESINTAMIL/AMAZING-ACTIVITIES-IN-TAMIL.pdf", "source": "internetarchive", "page_no": 9, "identifier": "AMAZINGACTIVITIESINTAMIL", "pdf_name": "AMAZING-ACTIVITIES-IN-TAMIL.pdf", "text": "1-செ.மீ. கட்டம் தாள்\nஅட்டை\n(10 செ.மீ. x 20 செ.மீ.)\nX\nமுக்கோணத்தின் பரப்பளவு\n1.மேல் முனைகளில் துளைகளை உருவாக்கவும்.\n2. ஏ மற்றும் பி - இல் துளைகளை உ ருவாக்குங்கள் ஒரு மீள் நூலை துளைகளில் நுழைத்து முடிச்சுகள் போடவும்.\n4. சி-யை நகர்த்தி இன்னொரு முக்கோணம் உருவாக்கி, அதன் பரப்பளவை அளக்கவும்.\nஆணி\nமீள் நூல்\n3. மீளை சி -புள்ளிக்கு இழுக்கவும்.\nஏபிசி-முக்கோணம் செய்ய துளையில் ஆணியை சொருகவும்.\nஅதன் பரப்பளவை மதிப்பிட முக்கோணத்தில் உள்ள சதுரங்களை எண்ணவும்.\nஅரை சதுரத்திற்கு குறைவானதை விடுத்து, அதிகமானதை ஒன்று என கணக்கிடவும்.\n5.இந்த அனைத்து முக்கோணங்களுக்கும் அடிப்பாகமும், குத்துயரமும் ஒன்றுதான், என்வே, அவற்றின் பரப்பளவும் ஒன்றுதான்.\n1\n"}